deimos_client/__init__.py
deimos_client/base_client_handler.py
deimos_client/client_oss.py
deimos_client/client_s3.py
deimos_client/client_tos.py
deimos_client/exception.py
deimos_client/file_client.py
deimos_client/file_management.py
deimos_client/utils.py
deimos_client-0.1.9.dist-info/METADATA
deimos_client-0.1.9.dist-info/WHEEL
deimos_client-0.1.9.dist-info/RECORD
