Metadata-Version: 2.4
Name: deimos_client
Version: 0.1.9
Summary: Deimos client for handling backend requests
Author-email: Logan <logan@deemos.com>
Requires-Dist: boto3
Requires-Dist: kombu
Requires-Dist: opencv-python
Requires-Dist: oss2
Requires-Dist: requests
Requires-Dist: tos
